<?xml version="1.0" encoding="UTF-8"?>
<con:resource name="" path="testString" id="2409225f-5a7d-4a39-a87e-efa9f85391be" xmlns:xsi="http://www.w3.org/2001/XMLSchema-instance" xmlns:con="http://eviware.com/soapui/config">
  <con:settings>
    <con:setting id="2409225f-5a7d-4a39-a87e-efa9f85391befileName">testString</con:setting>
  </con:settings>
  <con:parameters/>
  <con:method name="" id="774a0f52-eb4f-4b3e-9a57-67aad44c0e0b" method="GET">
    <con:settings/>
    <con:parameters>
      <con:parameter>
        <con:name>t</con:name>
        <con:value xsi:nil="true"/>
        <con:style>QUERY</con:style>
        <con:default xsi:nil="true"/>
      </con:parameter>
    </con:parameters>
    <con:request name="Request 1" id="ab33776d-153c-4476-8b98-61e4df5ac939" mediaType="application/json">
      <con:settings/>
      <con:endpoint>http://rapis02.aqa.com.ru</con:endpoint>
      <con:credentials>
        <con:selectedAuthProfile>No Authorization</con:selectedAuthProfile>
        <con:authType>No Authorization</con:authType>
      </con:credentials>
      <con:parameters/>
    </con:request>
  </con:method>
</con:resource>
